CodeKit/__init__.py
CodeKit/builder.py
CodeKit/timer.py
CodeKit/to_string.py
CodeKit-0.2.dist-info/METADATA
CodeKit-0.2.dist-info/WHEEL
CodeKit-0.2.dist-info/license
CodeKit-0.2.dist-info/top_level.txt
CodeKit-0.2.dist-info/RECORD
