Metadata-Version: 2.1
Name: CodeKit
Version: 0.2
Summary: Codekit provides functions and decorators to assist developers in coding.
Home-page: https://github.com/ErickRen2023/CodeKit
Author: ErickRen
Author-email: erickren2022@outlook.com
Classifier: Programming Language :: Python :: 3
Classifier: License :: OSI Approved :: MIT License
Classifier: Operating System :: OS Independent
License-File: license
